jk_utils/AmountOfBytes.py
jk_utils/AsyncRunner.py
jk_utils/Bytes.py
jk_utils/Cache.py
jk_utils/ChModValue.py
jk_utils/ChangedFlag.py
jk_utils/CmdLineParser.py
jk_utils/DataMatrix.py
jk_utils/DelayedKeyboardInterrupt.py
jk_utils/EnumBase.py
jk_utils/GracefullyHandleInterrupts.py
jk_utils/GracefullyHandleKeyboardInterrupt.py
jk_utils/ImplementationError.py
jk_utils/InterruptedException.py
jk_utils/MultiCounterDict.py
jk_utils/MutableString.py
jk_utils/ObservableEvent.py
jk_utils/PIDFile.py
jk_utils/PersistentProperties.py
jk_utils/RandomStateID.py
jk_utils/RoundRobinSequence.py
jk_utils/Stack.py
jk_utils/StateManager.py
jk_utils/TerminationFlag.py
jk_utils/TextCanvas.py
jk_utils/TextOutputBuffer.py
jk_utils/TextTable.py
jk_utils/TimeLimitedCache.py
jk_utils/TimeStamp.py
jk_utils/Timer.py
jk_utils/TypedValue.py
jk_utils/VolatileValue.py
jk_utils/__init__.py
jk_utils/arp.py
jk_utils/array.py
jk_utils/check.py
jk_utils/datanodes.py
jk_utils/datatypes.py
jk_utils/deferred.py
jk_utils/deprecated.py
jk_utils/dtutils.py
jk_utils/duration.py
jk_utils/file_rw.py
jk_utils/fsutils.py
jk_utils/hex.py
jk_utils/ip.py
jk_utils/mac.py
jk_utils/oop.py
jk_utils/pathutils.py
jk_utils/ping.py
jk_utils/processes.py
jk_utils/python.py
jk_utils/pythonmodules.py
jk_utils/re.py
jk_utils/reflection.py
jk_utils/rng.py
jk_utils/showCapacityProgress.py
jk_utils/tokenizer.py
jk_utils/users.py
jk_utils/async/TabularWriterMediaWiki.py
jk_utils/async/TabularWriterSTDOUT.py
jk_utils/async/__init__.py
jk_utils/async/queues.py
jk_utils/color/RGB.py
jk_utils/color/RGBSpectrum.py
jk_utils/color/RGBSpectrumBuilder.py
jk_utils/color/__init__.py
jk_utils/datetime/D.py
jk_utils/datetime/T1.py
jk_utils/datetime/T5.py
jk_utils/datetime/TApprox.py
jk_utils/datetime/__init__.py
jk_utils/datetime/dateiterator.py
jk_utils/datetime/timeiterator5.py
jk_utils/tokenizer2/AbstractTokenPattern.py
jk_utils/tokenizer2/RegExBasedTableTokenizer.py
jk_utils/tokenizer2/RegExBasedTokenizer.py
jk_utils/tokenizer2/Token.py
jk_utils-0.2025.3.8.dist-info/WHEEL
jk_utils-0.2025.3.8.dist-info/METADATA
jk_utils-0.2025.3.8.dist-info/RECORD
