Metadata-Version: 2.1
Name: jk_utils
Version: 0.2025.3.8
Summary: This python module provides various utility functions and classes.
Keywords: utilities
Author-email: Jürgen Knauth <pubsrc@binary-overflow.de>
Maintainer-email: Jürgen Knauth <pubsrc@binary-overflow.de>
Requires-Python: >=3.8
Classifier: Development Status :: 5 - Production/Stable
Classifier: License :: OSI Approved :: Apache Software License
Classifier: Programming Language :: Python :: 3
Requires-Dist: sortedcontainers
Requires-Dist: jk_simpleexec
Requires-Dist: jk_logging
Requires-Dist: jk_version
